pyhocon_fix/__init__.py
pyhocon_fix/config_parser.py
pyhocon_fix/config_tree.py
pyhocon_fix/exceptions.py
pyhocon_fix/tool.py
pyhocon_fix-0.0.2.dist-info/DESCRIPTION.rst
pyhocon_fix-0.0.2.dist-info/METADATA
pyhocon_fix-0.0.2.dist-info/RECORD
pyhocon_fix-0.0.2.dist-info/WHEEL
pyhocon_fix-0.0.2.dist-info/metadata.json
pyhocon_fix-0.0.2.dist-info/top_level.txt
